{
  "lang": "en",
  "domain": "https://meet.jit.si",
  "auto_hide_menu_timer": 10,
  "auto_pin_local_sharing": false,
  "min_part_tile_view": 2,
  "disable_self_view": false,
  "audio_only": false,
  "disable_menu": false,
  "tts": {
    "ivr": {
      "available": true,
      "speaker_on": true
    },
    "ui_helper": {
      "available": true,
      "speaker_on": false
    },
    "engine": "local_files",
    "format": "mp3"
  },
  "ivr": {
    "enabled": true,
    "number": 0,
    "confmapper_url": "",
    "confmapper_endpoint": "",
    "auth_url": "",
    "secure_regexp": ".*",
    "confmapper_timeout": 5000,
    "conference_code": {
      "min_length": 2,
      "max_length": 10
    }
  },
  "shortcuts":{
    "show-dtmf-menu": "h",
    "toggle-audio": "m",
    "toggle-video": "v",
    "toggle-chat": "c",
    "toggle-tile-view": "w",
    "toggle-raise-hand" : "r",
    "toggle-tts" : "x"
  }
}
